proalgotrader_manager/__init__.py
proalgotrader_manager/main.py
proalgotrader_manager/runner.py
proalgotrader_manager/libs/__init__.py
proalgotrader_manager/libs/args_manager.py
proalgotrader_manager/libs/router.py
proalgotrader_manager/libs/schedule_tasks.py
proalgotrader_manager/libs/tasks/__init__.py
proalgotrader_manager/libs/tasks/local_task.py
proalgotrader_manager/libs/tasks/production_task.py
proalgotrader_manager/payloads/__init__.py
proalgotrader_manager/payloads/update_state_request.py
proalgotrader_manager/router/__init__.py
proalgotrader_manager/router/algo_session.py
proalgotrader_manager/router/home.py
proalgotrader_manager-0.0.4.dist-info/METADATA
proalgotrader_manager-0.0.4.dist-info/WHEEL
proalgotrader_manager-0.0.4.dist-info/top_level.txt
proalgotrader_manager-0.0.4.dist-info/RECORD
