Metadata-Version: 2.1
Name: proalgotrader-manager
Version: 0.0.4
Summary: ProAlgoTrader Manager
Home-page: https://github.com/krunaldodiya/proalgotrader_manager
Author: Krunal Dodiya
Author-email: kunal.dodiya1@gmail.com
Classifier: Programming Language :: Python :: 3
Classifier: Operating System :: OS Independent
Requires-Dist: fastapi
Requires-Dist: uvicorn
Requires-Dist: apscheduler
